src/__init__.py
src/general/__init__.py
src/general/utils.py
src/graph/__init__.py
src/graph/distance.py
src/graph/enumeration.py
src/graph/manipulation.py
src/graph/matching.py
src/graph/polynomial.py
src/posets/__init__.py
src/posets/example_posets.py
src/posets/poset.py
src/posets/utils.py
tests/__init__.py
tests/general/__init__.py
tests/general/test_utils.py
tusc/__init__.py
tusc/general/__init__.py
tusc/general/utils.py
tusc/graph/__init__.py
tusc/graph/distance.py
tusc/graph/enumeration.py
tusc/graph/manipulation.py
tusc/graph/matching.py
tusc/graph/polynomial.py
tusc/posets/__init__.py
tusc/posets/example_posets.py
tusc/posets/poset.py
tusc/posets/utils.py
tusc-0.0.2.dist-info/LICENSE.md
tusc-0.0.2.dist-info/METADATA
tusc-0.0.2.dist-info/WHEEL
tusc-0.0.2.dist-info/top_level.txt
tusc-0.0.2.dist-info/RECORD
