Metadata-Version: 2.1
Name: tusc
Version: 0.0.2
Summary: a Python library providing tools for combinatorial maths
Home-page: https://github.com/lucasmccabe/tusc
Author: Lucas H. McCabe
Author-email: lucasmccabe@gwu.edu
License: UNKNOWN
Platform: UNKNOWN
Classifier: Programming Language :: Python :: 3
Classifier: License :: OSI Approved :: MIT License
Classifier: Operating System :: OS Independent
Requires-Python: >=3.8
